nablachem/__init__.py
nablachem/alchemy.py
nablachem/analyticgrads/AP_class.py
nablachem/analyticgrads/LICENSE
nablachem/analyticgrads/test.py
nablachem/cache/space-approx.msgpack.gz
nablachem/cache/space-compare.msgpack.gz
nablachem/cache/space-exact.msgpack.gz
nablachem/dimensionality.py
nablachem/space/__init__.py
nablachem/space/algos.py
nablachem/space/approximate.py
nablachem/space/editdistance.py
nablachem/space/exact.py
nablachem/space/utils.py
nablachem/utils/connsampler.py
nablachem/utils/graph.py
nablachem-25.9.dist-info/LICENSE
nablachem-25.9.dist-info/METADATA
nablachem-25.9.dist-info/WHEEL
nablachem-25.9.dist-info/RECORD
